techfactsdb/__init__.py
techfactsdb/data.py
techfactsdb-0.1.0.dist-info/METADATA
techfactsdb-0.1.0.dist-info/WHEEL
techfactsdb-0.1.0.dist-info/top_level.txt
techfactsdb-0.1.0.dist-info/RECORD
