Metadata-Version: 2.4
Name: techfactsdb
Version: 0.1.0
Summary: My custom module
Author: Abhiram
